maya_cli/__init__.py
maya_cli/cli.py
maya_cli/project_generator.py
maya_cli/refactor.py
maya_cli/scripts/__init__.py
maya_cli/scripts/optimize.py
maya_cli-0.1.4.dist-info/METADATA
maya_cli-0.1.4.dist-info/WHEEL
maya_cli-0.1.4.dist-info/entry_points.txt
maya_cli-0.1.4.dist-info/top_level.txt
maya_cli-0.1.4.dist-info/RECORD
