Metadata-Version: 2.2
Name: maya-cli
Version: 0.1.4
Summary: Maya CLI - AI Project Generator
Home-page: https://github.com/anointingmayami/Maya.ai
Author: King Anointing Joseph Mayami
Author-email: anointingmayami@gmail.com
Classifier: Programming Language :: Python :: 3
Classifier: License :: OSI Approved :: GNU General Public License v3 (GPLv3)
Classifier: Operating System :: OS Independent
Requires-Python: >=3.7
Requires-Dist: click
Dynamic: author
Dynamic: author-email
Dynamic: classifier
Dynamic: description
Dynamic: description-content-type
Dynamic: home-page
Dynamic: requires-dist
Dynamic: requires-python
Dynamic: summary
